sweetmorse/__init__.py
sweetmorse/constants.py
sweetmorse/main.py
sweetmorse/morse.py
sweetmorse-1.1.0.dist-info/DESCRIPTION.rst
sweetmorse-1.1.0.dist-info/METADATA
sweetmorse-1.1.0.dist-info/RECORD
sweetmorse-1.1.0.dist-info/WHEEL
sweetmorse-1.1.0.dist-info/entry_points.txt
sweetmorse-1.1.0.dist-info/metadata.json
sweetmorse-1.1.0.dist-info/top_level.txt
